py_lab_hal/__init__.py
py_lab_hal/builder.py
py_lab_hal/scan.py
py_lab_hal/cominterface/__init__.py
py_lab_hal/cominterface/acute.py
py_lab_hal/cominterface/cominterface.py
py_lab_hal/cominterface/debug.py
py_lab_hal/cominterface/dmx.py
py_lab_hal/cominterface/hislip.py
py_lab_hal/cominterface/http.py
py_lab_hal/cominterface/pylabhalboard.py
py_lab_hal/cominterface/serial.py
py_lab_hal/cominterface/socket.py
py_lab_hal/cominterface/usb.py
py_lab_hal/cominterface/usbmonsoon.py
py_lab_hal/cominterface/usbtmc.py
py_lab_hal/cominterface/visa.py
py_lab_hal/cominterface/vxi11.py
py_lab_hal/data_logger/__init__.py
py_lab_hal/data_logger/data_logger.py
py_lab_hal/data_logger/test_logger.py
py_lab_hal/datagram/__init__.py
py_lab_hal/datagram/datagram.py
py_lab_hal/datagrame/__init__.py
py_lab_hal/datagrame/datagrame.py
py_lab_hal/environment/__init__.py
py_lab_hal/environment/py_lab_hal_env.py
py_lab_hal/instrument/__init__.py
py_lab_hal/instrument/instrument.py
py_lab_hal/instrument/ac_pa/__init__.py
py_lab_hal/instrument/ac_pa/ac_pa.py
py_lab_hal/instrument/acpsu/__init__.py
py_lab_hal/instrument/acpsu/acpsu.py
py_lab_hal/instrument/arm/__init__.py
py_lab_hal/instrument/arm/arch.py
py_lab_hal/instrument/arm/arm.py
py_lab_hal/instrument/arm/dexarm.py
py_lab_hal/instrument/battery_emulator/__init__.py
py_lab_hal/instrument/battery_emulator/battery_emulator.py
py_lab_hal/instrument/battery_emulator/keysight_663xxx.py
py_lab_hal/instrument/battery_emulator/keysight_n6705c.py
py_lab_hal/instrument/color_meter/__init__.py
py_lab_hal/instrument/color_meter/admesy_hyperion.py
py_lab_hal/instrument/color_meter/color_meter.py
py_lab_hal/instrument/common/__init__.py
py_lab_hal/instrument/common/keysight/__init__.py
py_lab_hal/instrument/common/keysight/keysight_dmm.py
py_lab_hal/instrument/common/keysight/keysight_n6705c.py
py_lab_hal/instrument/dcpsu/__init__.py
py_lab_hal/instrument/dcpsu/aimtticpx_4000dp.py
py_lab_hal/instrument/dcpsu/dcpsu.py
py_lab_hal-2.5.20241201.dist-info/LICENSE
py_lab_hal-2.5.20241201.dist-info/METADATA
py_lab_hal-2.5.20241201.dist-info/WHEEL
py_lab_hal-2.5.20241201.dist-info/top_level.txt
py_lab_hal-2.5.20241201.dist-info/RECORD
