Metadata-Version: 2.1
Name: py-lab-hal
Version: 2.5.20241201
Summary: A test instrument Hardware Abstraction Layer (HAL)
Project-URL: Homepage, https://github.com/google/py-lab-hal
Project-URL: Issues, https://github.com/google/py-lab-hal/issues
Classifier: Development Status :: 5 - Production/Stable
Classifier: Intended Audience :: Developers
Classifier: License :: OSI Approved :: Apache Software License
Classifier: Programming Language :: Python
Classifier: Programming Language :: Python :: 3
Classifier: Programming Language :: Python :: 3.10
Classifier: Programming Language :: Python :: 3.11
Classifier: Programming Language :: Python :: 3.12
Classifier: Programming Language :: Python :: 3 :: Only
Classifier: Topic :: Software Development
Classifier: Topic :: System :: Hardware :: Hardware Drivers
Classifier: Topic :: Scientific/Engineering
Classifier: Operating System :: Microsoft :: Windows
Classifier: Operating System :: POSIX
Classifier: Operating System :: Unix
Classifier: Operating System :: MacOS
Requires-Python: <3.13,>=3.9
License-File: LICENSE
Requires-Dist: dataclasses-json~=0.6.4
Requires-Dist: grpcio~=1.62.0
Requires-Dist: ifcfg~=0.24
Requires-Dist: libusb~=1.0.27
Requires-Dist: monsoon~=0.1.88
Requires-Dist: pyserial~=3.5
Requires-Dist: python-usbtmc~=0.8
Requires-Dist: python-vxi11~=0.9
Requires-Dist: PyVISA~=1.14.1
Requires-Dist: requests~=2.32.3
Provides-Extra: tests
Requires-Dist: pytest~=8.2.0; extra == "tests"
